llama_index/embeddings/google_genai/__init__.py
llama_index/embeddings/google_genai/base.py
llama_index_embeddings_google_genai-0.3.0.dist-info/METADATA
llama_index_embeddings_google_genai-0.3.0.dist-info/WHEEL
llama_index_embeddings_google_genai-0.3.0.dist-info/licenses/LICENSE
llama_index_embeddings_google_genai-0.3.0.dist-info/RECORD
