Metadata-Version: 2.4
Name: llama-index-embeddings-google-genai
Version: 0.3.0
Summary: llama-index embeddings google genai integration
Author-email: Your Name <you@example.com>
License-Expression: MIT
License-File: LICENSE
Requires-Python: <4.0,>=3.9
Requires-Dist: google-genai<2,>=1.24.0
Requires-Dist: llama-index-core<0.14,>=0.13.0
